{
    "pageData": {
        "softwarePageData": {
            "customerReviewsUrl": "https://itunes.apple.com/us/customer-reviews/id544007664?dataOnly=true&displayable-kind=11", 
            "customersAlsoBoughtApps": [
                331975235, 
                440159265, 
                438596432, 
                438429273, 
                430623298, 
                487225881, 
                505766376, 
                583555212, 
                486781045, 
                501945443, 
                475976577, 
                597851882, 
                441457218
            ], 
            "sellerLabel": "Seller", 
            "isFatBinary": 1, 
            "topApps": {
                "ipad": {
                    "ids": [
                        539297584, 
                        535811906, 
                        396799352, 
                        527445936, 
                        576731399, 
                        659614190, 
                        448639966, 
                        709020278, 
                        512727332, 
                        543577420, 
                        331975235, 
                        587366035, 
                        843006560, 
                        756298885
                    ], 
                    "title": "Top Free iPad Photo & Video Apps"
                }, 
                "iphone": {
                    "ids": [
                        389801252, 
                        447188370, 
                        592447445, 
                        576649830, 
                        588199307, 
                        543577420, 
                        527445936, 
                        512727332, 
                        448639966, 
                        454768104, 
                        577423493, 
                        576731399, 
                        587366035, 
                        756298885
                    ], 
                    "title": "Top Free iPhone Photo & Video Apps"
                }
            }, 
            "rating-and-advisories": {
                "advisories": [
                    "Infrequent/Mild Sexual Content and Nudity", 
                    "Infrequent/Mild Cartoon or Fantasy Violence", 
                    "Infrequent/Mild Profanity or Crude Humor", 
                    "Infrequent/Mild Alcohol, Tobacco, or Drug Use or References", 
                    "Infrequent/Mild Simulated Gambling", 
                    "Infrequent/Mild Realistic Violence", 
                    "Infrequent/Mild Mature/Suggestive Themes", 
                    "Infrequent/Mild Medical/Treatment Information", 
                    "Infrequent/Mild Horror/Fear Themes"
                ], 
                "rating-text": "Rated 12+ for the following:"
            }, 
            "moreByThisDeveloper": [
                535886823, 
                284815942, 
                680819774, 
                422689480, 
                585027354, 
                293622097, 
                507874739, 
                842842640, 
                643496868, 
                447119634, 
                414706506, 
                842849113
            ], 
            "appRatingsLearnMoreUrl": "https://itunes.apple.com/WebObjects/MZStore.woa/wa/appRatings?cc=us", 
            "versionHistory": [
                {
                    "releaseDate": "2014-11-12T21:53:12Z", 
                    "releaseNotes": "Music on YouTube is better than ever. Find your favorite videos and get recommendations on a new music homepage, listen to an endless YouTube Mix based on your favorite song or artist, and play albums right from search.", 
                    "versionString": "2.16.11441"
                }, 
                {
                    "releaseDate": "2014-10-23T23:24:30Z", 
                    "releaseNotes": "Fixes to iPad layout.", 
                    "versionString": "2.13.11403"
                }, 
                {
                    "releaseDate": "2014-10-15T16:14:46Z", 
                    "releaseNotes": "Now updated for iPhone 6. Includes bug fixes to:\n* Prevent the status bar from overlapping the UI\n* Address keyboard orientation issues\n* Make scrubbing more responsive\n* Show all playlists when adding videos", 
                    "versionString": "2.13"
                }, 
                {
                    "releaseDate": "2014-10-07T15:35:57Z", 
                    "releaseNotes": "Minor bug fixes and stabilization.", 
                    "versionString": "2.10.3"
                }, 
                {
                    "releaseDate": "2014-09-17T21:09:13Z", 
                    "releaseNotes": "Stabilization and minor bug fixes.", 
                    "versionString": "2.10.2"
                }, 
                {
                    "releaseDate": "2014-09-04T00:49:50Z", 
                    "releaseNotes": "Bug fixes and stabilization.", 
                    "versionString": "2.10.0"
                }, 
                {
                    "releaseDate": "2014-08-20T19:37:14Z", 
                    "releaseNotes": "Fixes for top crashes.", 
                    "versionString": "2.9.3"
                }, 
                {
                    "releaseDate": "2014-08-07T18:13:50Z", 
                    "releaseNotes": "Stabilization and minor bug fixes.", 
                    "versionString": "2.9.0"
                }, 
                {
                    "releaseDate": "2014-06-17T22:37:22Z", 
                    "releaseNotes": "Upload videos to YouTube in one quick step.", 
                    "versionString": "2.7.1"
                }, 
                {
                    "releaseDate": "2014-06-11T17:23:00Z", 
                    "releaseNotes": "Stabilization and minor bug fixes.", 
                    "versionString": "2.7.0"
                }, 
                {
                    "releaseDate": "2014-04-30T18:04:12Z", 
                    "releaseNotes": "Stabilization and minor bug fixes.", 
                    "versionString": "2.6.0"
                }, 
                {
                    "releaseDate": "2014-04-01T16:32:51Z", 
                    "releaseNotes": "Stabilization and minor bug fixes.", 
                    "versionString": "2.5.1"
                }, 
                {
                    "releaseDate": "2014-03-17T21:04:56Z", 
                    "releaseNotes": "* Share and like playlists\n* Quickly access your favorite playlists from the Guide\n* Reply to comments and delete your own\n* See if a comment was shared privately or publicly", 
                    "versionString": "2.5.0"
                }, 
                {
                    "releaseDate": "2014-01-21T18:31:33Z", 
                    "releaseNotes": "Stabilization and minor bug fixes.", 
                    "versionString": "2.3.1"
                }, 
                {
                    "releaseDate": "2014-01-08T00:30:51Z", 
                    "releaseNotes": "* Find videos, playlists and channels together in search results\n* Formatting, positioning and user settings for captions / subtitles\n* iOS 7 keyboard and other improvements", 
                    "versionString": "2.3.0"
                }, 
                {
                    "releaseDate": "2013-10-15T19:23:02Z", 
                    "releaseNotes": "* Choose your video quality while on Wi-Fi\n* Accessibility improvements\n* iOS 7 compatibility improvements", 
                    "versionString": "2.2.0"
                }, 
                {
                    "releaseDate": "2013-09-26T18:41:14Z", 
                    "releaseNotes": "* Minor bug fixes and stability improvements\n* iOS 7 compatible", 
                    "versionString": "2.1.0"
                }, 
                {
                    "releaseDate": "2013-08-20T17:23:50Z", 
                    "releaseNotes": "* Watch a video while searching for the next one, just like picture-in-picture\n* Search for playlists and use the \u201cplay all\u201d button for endless entertainment", 
                    "versionString": "2.0"
                }, 
                {
                    "releaseDate": "2013-06-20T17:21:07Z", 
                    "releaseNotes": "* Video suggestion overlays for what to watch next\n* Closed captions for live streams \n* Stability improvements, including fix for application crashes", 
                    "versionString": "1.4"
                }, 
                {
                    "releaseDate": "2013-04-15T18:14:45Z", 
                    "releaseNotes": "* Quick access to new uploads from subscriptions via \"My Subscriptions\" feed on the Guide  \n* Access to Live streams \n* Queue up videos to play on TV\n* One Channel branding for video creator channels\n* Stability and performance improvements", 
                    "versionString": "1.3"
                }, 
                {
                    "releaseDate": "2013-02-28T17:50:55Z", 
                    "releaseNotes": "* Send to TV: control YouTube on TV, Xbox or Sony PS3 from the app\n* Improved streaming over slow WiFi connection\n* Ability to record and upload video via YouTube Capture\n* Overall stability improvements", 
                    "versionString": "1.2.1"
                }, 
                {
                    "releaseDate": "2012-12-04T21:49:52Z", 
                    "releaseNotes": "* Optimized for iPad and iPhone 5\n* Stream videos with AirPlay \n* Tap logo to open your Guide of channels\n* Add and remove videos from your playlists\n* Clickable links in video descriptions\n* Improved accessibility with VoiceOver", 
                    "versionString": "1.1.0.4136"
                }, 
                {
                    "releaseDate": "2012-09-10T07:11:57Z", 
                    "releaseNotes": "minor bugfixes.", 
                    "versionString": "1.0.1.3063"
                }, 
                {
                    "releaseDate": "2012-08-12T17:22:41Z", 
                    "releaseNotes": null, 
                    "versionString": "1.0.0.2939"
                }
            ], 
            "id": 544007664
        }, 
        "metricsBase": {
            "pageDetails": "Google, Inc._YouTube", 
            "pageId": "544007664", 
            "language": "1", 
            "serverInstance": "2125797", 
            "platformId": "28", 
            "storeFront": "143441", 
            "storeFrontHeader": "143441-1,28", 
            "environmentDataCenter": "ST11", 
            "pageType": "Software", 
            "platformName": "iTunes12", 
            "page": "Software_544007664"
        }, 
        "footerBreadcrumbs": [
            {
                "url": "https://itunes.apple.com/us/store", 
                "label": "iTunes Store"
            }, 
            {
                "url": "https://itunes.apple.com/us/genre/ios/id36?mt=8", 
                "label": "App Store"
            }, 
            {
                "url": "https://itunes.apple.com/us/genre/ios-photo-video/id6008?mt=8", 
                "label": "Photo & Video"
            }, 
            {
                "url": "https://itunes.apple.com/us/artist/google-inc./id281956209", 
                "label": "Google, Inc."
            }, 
            {
                "url": "https://itunes.apple.com/us/app/youtube/id544007664?mt=8", 
                "label": "YouTube"
            }
        ], 
        "copyright": "Copyright \u00a9 2014 Apple Inc.", 
        "privacyLink": {
            "url": "https://www.apple.com/legal/privacy/", 
            "label": "Privacy Policy"
        }, 
        "breadcrumbs": [
            {
                "url": "https://itunes.apple.com/us/genre/ios/id36?mt=8", 
                "label": "App Store"
            }, 
            {
                "url": "https://itunes.apple.com/us/genre/ios-photo-video/id6008?mt=8", 
                "label": "Photo & Video"
            }, 
            {
                "url": "https://itunes.apple.com/us/artist/google-inc./id281956209", 
                "label": "Google, Inc."
            }
        ], 
        "sf6ResourceImagePath": "https://s.mzstatic.com/htmlResources/9548/frameworks-sf6/images/", 
        "omnitureMetrics": {
            "shouldTrackBrowserPlugins": false, 
            "format": "HTML", 
            "isClickMetricsEnabled": false, 
            "isBuyMetricsEnabled": true, 
            "isPageMetricsEnabled": true, 
            "products": "Google, Inc.-YouTube-544007664", 
            "pageName": "Software-US-Google, Inc.-YouTube-544007664", 
            "shouldIncludeRecommendationInfoInClickMetrics": true, 
            "channel": "Software Pages"
        }, 
        "mediaType": "8", 
        "navBarSelectedMenu": "App Store", 
        "legalLink": {
            "url": "https://www.apple.com/legal/", 
            "label": "All rights reserved."
        }, 
        "metrics": {
            "fields": {}, 
            "config": {
                "blacklistedFields": [
                    "capacitySystem", 
                    "capacitySystemAvailable", 
                    "capacityDisk", 
                    "capacityData", 
                    "capacityDataAvailable"
                ]
            }
        }, 
        "resourceImagePath": "https://s.mzstatic.com/htmlResources/9548/di6-storefront/images/", 
        "resourceBasePath": "/htmlResources/9548/files/", 
        "flagLink": {
            "url": "https://itunes.apple.com/WebObjects/MZStore.woa/wa/countrySelectorPage?cc=us", 
            "imageSrc": "https://s.mzstatic.com/images/flags/-dsi-30/usa.png", 
            "imageAltText": "My Store: United States, Choose Store"
        }, 
        "resourceImagePathFrameworksDt6": "https://s.mzstatic.com/htmlResources/9548/frameworks-dt6/images/", 
        "termsLink": {
            "url": "https://www.apple.com/legal/itunes/us/terms.html", 
            "label": "Terms and Conditions"
        }, 
        "pageComponent": "software_page", 
        "footerLinks": {
            "sections": [
                {
                    "links": [
                        {
                            "url": "https://itunes.apple.com/WebObjects/MZStore.woa/wa/viewGrouping?cc=us&id=1", 
                            "label": "Music"
                        }, 
                        {
                            "url": "https://itunes.apple.com/WebObjects/MZStore.woa/wa/viewGrouping?cc=us&id=39", 
                            "label": "Movies"
                        }, 
                        {
                            "url": "https://itunes.apple.com/WebObjects/MZStore.woa/wa/viewGrouping?cc=us&id=37", 
                            "label": "TV Shows"
                        }, 
                        {
                            "url": "https://itunes.apple.com/WebObjects/MZStore.woa/wa/viewGrouping?cc=us&id=25204&mt=8", 
                            "label": "App Store"
                        }, 
                        {
                            "url": "https://itunes.apple.com/WebObjects/MZStore.woa/wa/viewGrouping?cc=us&id=27820&mt=11", 
                            "label": "Books"
                        }, 
                        {
                            "url": "https://itunes.apple.com/WebObjects/MZStore.woa/wa/viewGrouping?cc=us&id=33&mt=2", 
                            "label": "Podcasts"
                        }, 
                        {
                            "url": "https://itunes.apple.com/WebObjects/MZStore.woa/wa/viewGrouping?cc=us&id=28", 
                            "label": "Audiobooks"
                        }, 
                        {
                            "url": "https://itunes.apple.com/WebObjects/MZStore.woa/wa/viewGenre?id=40000000&mt=10", 
                            "label": "iTunes U"
                        }
                    ], 
                    "title": "Explore"
                }, 
                {
                    "links": [
                        {
                            "url": "itsradio://stations", 
                            "target": "_blank", 
                            "label": "iTunes Radio"
                        }, 
                        {
                            "url": "https://itunes.apple.com/WebObjects/MZStore.woa/wa/redirectToBrowse", 
                            "label": "Browse"
                        }, 
                        {
                            "url": "https://itunes.apple.com/us/collection/featured-pre-orders/id1?fcId=673203643", 
                            "label": "Featured Pre-Orders"
                        }, 
                        {
                            "url": "https://se.itunes.apple.com/WebObjects/MZStoreElements.woa/wa/purchases?cc=us", 
                            "label": "Purchased"
                        }, 
                        {
                            "url": "https://itunes.apple.com/WebObjects/MZStore.woa/wa/learnMore?about=purchases", 
                            "label": "iTunes Match"
                        }
                    ], 
                    "title": "Features"
                }, 
                {
                    "links": [
                        {
                            "url": "https://itunes.apple.com/WebObjects/MZStore.woa/wa/gotoiTunesSupport", 
                            "label": "Support"
                        }, 
                        {
                            "url": "https://www.apple.com/itunes/how-to/", 
                            "target": "_blank", 
                            "label": "iTunes Tutorials"
                        }, 
                        {
                            "url": "https://itunes.apple.com/WebObjects/MZStore.woa/wa/viewStaticPage?name=MovieRentals", 
                            "label": "Rent & Buy Movies"
                        }, 
                        {
                            "url": "https://itunes.apple.com/WebObjects/MZStore.woa/wa/viewCustomPage?name=LearnMoreAboutTV", 
                            "label": "Learn More About TV"
                        }, 
                        {
                            "url": "https://itunes.apple.com/WebObjects/MZStore.woa/wa/viewCustomPage?name=LearnMoreAboutInAppPurchases", 
                            "label": "In-App Purchases"
                        }, 
                        {
                            "url": "https://www.apple.com/support/systemstatus/", 
                            "target": "_blank", 
                            "label": "System Status"
                        }
                    ], 
                    "title": "Help"
                }, 
                {
                    "links": [
                        {
                            "url": "https://buy.itunes.apple.com/WebObjects/MZFinance.woa/wa/accountSummary", 
                            "label": "Account"
                        }, 
                        {
                            "url": "https://buy.itunes.apple.com/WebObjects/MZFinance.woa/wa/redeemLandingPage", 
                            "label": "Redeem"
                        }, 
                        {
                            "url": "https://se.itunes.apple.com/WebObjects/MZStoreElements.woa/wa/viewWishlist?cc=us", 
                            "label": "My Wish List"
                        }, 
                        {
                            "url": "https://itunes.apple.com/WebObjects/MZStore.woa/wa/countrySelectorPage", 
                            "label": "Change Country"
                        }
                    ], 
                    "title": "Manage"
                }
            ]
        }
    }, 
    "storePlatformData": {
        "product-dv-product": {
            "version": 1, 
            "results": {
                "544007664": {
                    "uber": null, 
                    "hasInAppPurchases": false, 
                    "releaseDate": "2012-09-11", 
                    "artistId": 281956209, 
                    "userRating": {
                        "ratingCountCurrentVersion": 2666, 
                        "valueCurrentVersion": 2.5, 
                        "value": 2.5, 
                        "ratingCount": 135534
                    }, 
                    "artistUrl": "https://itunes.apple.com/us/artist/google-inc./id281956209?mt=8", 
                    "itunesNotes": null, 
                    "id": 544007664, 
                    "bundleId": "com.google.ios.youtube", 
                    "genres": [
                        {
                            "url": "https://itunes.apple.com/us/genre/id6008", 
                            "name": "Photo & Video"
                        }, 
                        {
                            "url": "https://itunes.apple.com/us/genre/id6016", 
                            "name": "Entertainment"
                        }
                    ], 
                    "copyright": "\u00a9 2014 Google Inc.", 
                    "supportsPassbook": false, 
                    "description": {
                        "standard": "Get the official YouTube app for iPhone and iPad. Catch up with your favorite channels, enjoy the world\u2019s largest music collection, and share easily with friends. Watch the latest videos and playlists on the couch or on the go.\n\nYouTube, your way\n* Discover videos and channels with recommendations just for you\n* Cast videos from your phone to Chromecast, other connected TV devices, and game consoles\n* Use playlists to save, organize, and share your favorite tracks\n\nEnjoy endless music\n* Find songs you love on your new personalized music homepage\n* Launch a YouTube Mix, an infinite playlist of songs with unlimited skips\n* Explore the world\u2019s music in YouTube\u2019s massive music catalog"
                    }, 
                    "softwareInfo": {
                        "privacyPolicyUrl": "http://www.google.com/intl/en/policies/privacy/", 
                        "supportUrl": "http://support.google.com/youtube?p=ytios_appstore", 
                        "languagesDisplayString": "English, Arabic, Bokm\u00e5l, Norwegian, Catalan, Chinese, Croatian, Czech, Danish, Dutch, Finnish, French, German, Greek, Hebrew, Hungarian, Indonesian, Italian, Japanese, Korean, Latvian, Lithuanian, Malay, Norwegian, Polish, Portuguese, Romanian, Russian, Slovak, Spanish, Swedish, Thai, Turkish, Ukrainian, Vietnamese", 
                        "seller": "Google, Inc.", 
                        "websiteUrl": null, 
                        "requirementsString": "Requires iOS 6.0 or later. Compatible with iPhone, iPad, and iPod touch. This app is optimized for iPhone\u00a05.", 
                        "eulaUrl": "https://itunes.apple.com/WebObjects/MZStore.woa/wa/viewEula?id=544007664"
                    }, 
                    "contentRating": {
                        "system": "GAMES", 
                        "advisories": [
                            "Infrequent/Mild Sexual Content and Nudity", 
                            "Infrequent/Mild Cartoon or Fantasy Violence", 
                            "Infrequent/Mild Profanity or Crude Humor", 
                            "Infrequent/Mild Alcohol, Tobacco, or Drug Use or References", 
                            "Infrequent/Mild Simulated Gambling", 
                            "Infrequent/Mild Realistic Violence", 
                            "Infrequent/Mild Mature/Suggestive Themes", 
                            "Infrequent/Mild Medical/Treatment Information", 
                            "Infrequent/Mild Horror/Fear Themes"
                        ], 
                        "value": 300, 
                        "rank": 3, 
                        "name": "12+"
                    }, 
                    "appBundleAdamIds": [], 
                    "shortUrl": "https://appsto.re/us/WxoBG.i", 
                    "ageBand": null, 
                    "familyShareEnabledDate": "0001-04-23T00:00:00Z", 
                    "deviceFamilies": [
                        "iphone", 
                        "ipad", 
                        "ipod"
                    ], 
                    "contentRatingsBySystem": {
                        "appsApple": {
                            "rank": 3, 
                            "advisories": [
                                "Infrequent/Mild Sexual Content and Nudity", 
                                "Infrequent/Mild Cartoon or Fantasy Violence", 
                                "Infrequent/Mild Profanity or Crude Humor", 
                                "Infrequent/Mild Alcohol, Tobacco, or Drug Use or References", 
                                "Infrequent/Mild Simulated Gambling", 
                                "Infrequent/Mild Realistic Violence", 
                                "Infrequent/Mild Mature/Suggestive Themes", 
                                "Infrequent/Mild Medical/Treatment Information", 
                                "Infrequent/Mild Horror/Fear Themes"
                            ], 
                            "name": "12+", 
                            "value": 300
                        }
                    }, 
                    "offers": [
                        {
                            "actionText": {
                                "downloaded": "Installed", 
                                "medium": "Get", 
                                "short": "Get", 
                                "downloading": "Installing", 
                                "long": "Get App"
                            }, 
                            "assets": [
                                {
                                    "flavor": "iosSoftware", 
                                    "size": 33359764
                                }
                            ], 
                            "priceFormatted": "$0.00", 
                            "price": 0, 
                            "version": {
                                "externalId": 782692675, 
                                "display": "2.16.11441"
                            }, 
                            "buyParams": "productType=C&price=0&salableAdamId=544007664&pricingParameters=STDQ&appExtVrsId=782692675", 
                            "type": "get"
                        }
                    ], 
                    "editorialBadgeInfo": {
                        "editorialBadgeType": "staffPick", 
                        "nameForDisplay": "Essentials"
                    }, 
                    "artwork": [
                        {
                            "url": "http://a4.mzstatic.com/us/r30/Purple3/v4/8e/30/06/8e3006a5-db0d-ccad-9100-337632ae466b/icon240x240.jpeg", 
                            "width": 240, 
                            "height": 240
                        }, 
                        {
                            "url": "http://a2.mzstatic.com/us/r30/Purple3/v4/8e/30/06/8e3006a5-db0d-ccad-9100-337632ae466b/icon1024x1024.png", 
                            "width": 1024, 
                            "height": 1024
                        }, 
                        {
                            "url": "http://a1.mzstatic.com/us/r30/Purple3/v4/8e/30/06/8e3006a5-db0d-ccad-9100-337632ae466b/icon440x440.jpeg", 
                            "width": 440, 
                            "height": 440
                        }, 
                        {
                            "url": "http://a2.mzstatic.com/us/r30/Purple3/v4/8e/30/06/8e3006a5-db0d-ccad-9100-337632ae466b/icon220x220.png", 
                            "width": 220, 
                            "height": 220
                        }, 
                        {
                            "url": "http://a2.mzstatic.com/us/r30/Purple3/v4/8e/30/06/8e3006a5-db0d-ccad-9100-337632ae466b/icon400x400.jpeg", 
                            "width": 400, 
                            "height": 400
                        }, 
                        {
                            "url": "http://a2.mzstatic.com/us/r30/Purple3/v4/8e/30/06/8e3006a5-db0d-ccad-9100-337632ae466b/icon512x512.png", 
                            "width": 512, 
                            "height": 512
                        }
                    ], 
                    "requiredCapabilities": "armv7 ", 
                    "name": "YouTube", 
                    "kind": "iosSoftware", 
                    "tellAFriendMessageContentsUrl": "https://userpub.itunes.apple.com/WebObjects/MZUserPublishing.woa/wa/tellAFriendEmailBody?cc=us&displayable-kind=11&id=544007664&name=s&type=14", 
                    "nameRaw": "YouTube", 
                    "url": "https://itunes.apple.com/us/app/youtube/id544007664?mt=8", 
                    "genreNames": [
                        "Photo & Video", 
                        "Entertainment"
                    ], 
                    "artistName": "Google, Inc.", 
                    "screenshotsByType": {
                        "ipad": [
                            [
                                {
                                    "url": "http://a5.mzstatic.com/us/r30/Purple5/v4/7f/2a/5f/7f2a5fee-58b1-b711-4ffe-5d539a766191/screen261x261-50.jpeg", 
                                    "width": 261, 
                                    "height": 196
                                }, 
                                {
                                    "url": "http://a2.mzstatic.com/us/r30/Purple5/v4/7f/2a/5f/7f2a5fee-58b1-b711-4ffe-5d539a766191/screen460x460.jpeg", 
                                    "width": 460, 
                                    "height": 345
                                }, 
                                {
                                    "url": "http://a1.mzstatic.com/us/r30/Purple5/v4/7f/2a/5f/7f2a5fee-58b1-b711-4ffe-5d539a766191/screen920x920.jpeg", 
                                    "width": 920, 
                                    "height": 690
                                }, 
                                {
                                    "url": "http://a5.mzstatic.com/us/r30/Purple5/v4/7f/2a/5f/7f2a5fee-58b1-b711-4ffe-5d539a766191/screen552x414.jpeg", 
                                    "width": 552, 
                                    "height": 414
                                }, 
                                {
                                    "url": "http://a1.mzstatic.com/us/r30/Purple5/v4/7f/2a/5f/7f2a5fee-58b1-b711-4ffe-5d539a766191/screen420x420.jpeg", 
                                    "width": 420, 
                                    "height": 315
                                }, 
                                {
                                    "url": "http://a4.mzstatic.com/us/r30/Purple5/v4/7f/2a/5f/7f2a5fee-58b1-b711-4ffe-5d539a766191/screen420x316.jpeg", 
                                    "width": 420, 
                                    "height": 315
                                }, 
                                {
                                    "url": "http://a1.mzstatic.com/us/r30/Purple5/v4/7f/2a/5f/7f2a5fee-58b1-b711-4ffe-5d539a766191/screen768x768.jpeg", 
                                    "width": 768, 
                                    "height": 576
                                }
                            ], 
                            [
                                {
                                    "url": "http://a4.mzstatic.com/us/r30/Purple5/v4/89/e5/ea/89e5ea29-5b35-171f-9a3f-ff25c3c6e682/screen261x261-50.jpeg", 
                                    "width": 196, 
                                    "height": 261
                                }, 
                                {
                                    "url": "http://a4.mzstatic.com/us/r30/Purple5/v4/89/e5/ea/89e5ea29-5b35-171f-9a3f-ff25c3c6e682/screen460x460.jpeg", 
                                    "width": 345, 
                                    "height": 460
                                }, 
                                {
                                    "url": "http://a3.mzstatic.com/us/r30/Purple5/v4/89/e5/ea/89e5ea29-5b35-171f-9a3f-ff25c3c6e682/screen920x920.jpeg", 
                                    "width": 690, 
                                    "height": 920
                                }, 
                                {
                                    "url": "http://a3.mzstatic.com/us/r30/Purple5/v4/89/e5/ea/89e5ea29-5b35-171f-9a3f-ff25c3c6e682/screen600x600.jpeg", 
                                    "width": 450, 
                                    "height": 600
                                }, 
                                {
                                    "url": "http://a3.mzstatic.com/us/r30/Purple5/v4/89/e5/ea/89e5ea29-5b35-171f-9a3f-ff25c3c6e682/screen310x414.jpeg", 
                                    "width": 310, 
                                    "height": 413
                                }, 
                                {
                                    "url": "http://a3.mzstatic.com/us/r30/Purple5/v4/89/e5/ea/89e5ea29-5b35-171f-9a3f-ff25c3c6e682/screen768x768.jpeg", 
                                    "width": 576, 
                                    "height": 768
                                }
                            ], 
                            [
                                {
                                    "url": "http://a4.mzstatic.com/us/r30/Purple5/v4/2f/67/13/2f671341-f50e-070f-1dec-e2ae8e75e032/screen261x261-50.jpeg", 
                                    "width": 196, 
                                    "height": 261
                                }, 
                                {
                                    "url": "http://a1.mzstatic.com/us/r30/Purple5/v4/2f/67/13/2f671341-f50e-070f-1dec-e2ae8e75e032/screen460x460.jpeg", 
                                    "width": 345, 
                                    "height": 460
                                }, 
                                {
                                    "url": "http://a5.mzstatic.com/us/r30/Purple5/v4/2f/67/13/2f671341-f50e-070f-1dec-e2ae8e75e032/screen920x920.jpeg", 
                                    "width": 690, 
                                    "height": 920
                                }, 
                                {
                                    "url": "http://a5.mzstatic.com/us/r30/Purple5/v4/2f/67/13/2f671341-f50e-070f-1dec-e2ae8e75e032/screen600x600.jpeg", 
                                    "width": 450, 
                                    "height": 600
                                }, 
                                {
                                    "url": "http://a5.mzstatic.com/us/r30/Purple5/v4/2f/67/13/2f671341-f50e-070f-1dec-e2ae8e75e032/screen310x414.jpeg", 
                                    "width": 310, 
                                    "height": 413
                                }, 
                                {
                                    "url": "http://a5.mzstatic.com/us/r30/Purple5/v4/2f/67/13/2f671341-f50e-070f-1dec-e2ae8e75e032/screen768x768.jpeg", 
                                    "width": 576, 
                                    "height": 768
                                }
                            ], 
                            [
                                {
                                    "url": "http://a5.mzstatic.com/us/r30/Purple5/v4/3d/3b/75/3d3b757b-3460-17ff-3e56-a7e5667e9283/screen261x261-50.jpeg", 
                                    "width": 196, 
                                    "height": 261
                                }, 
                                {
                                    "url": "http://a4.mzstatic.com/us/r30/Purple5/v4/3d/3b/75/3d3b757b-3460-17ff-3e56-a7e5667e9283/screen460x460.jpeg", 
                                    "width": 345, 
                                    "height": 460
                                }, 
                                {
                                    "url": "http://a3.mzstatic.com/us/r30/Purple5/v4/3d/3b/75/3d3b757b-3460-17ff-3e56-a7e5667e9283/screen920x920.jpeg", 
                                    "width": 690, 
                                    "height": 920
                                }, 
                                {
                                    "url": "http://a5.mzstatic.com/us/r30/Purple5/v4/3d/3b/75/3d3b757b-3460-17ff-3e56-a7e5667e9283/screen600x600.jpeg", 
                                    "width": 450, 
                                    "height": 600
                                }, 
                                {
                                    "url": "http://a3.mzstatic.com/us/r30/Purple5/v4/3d/3b/75/3d3b757b-3460-17ff-3e56-a7e5667e9283/screen310x414.jpeg", 
                                    "width": 310, 
                                    "height": 413
                                }, 
                                {
                                    "url": "http://a3.mzstatic.com/us/r30/Purple5/v4/3d/3b/75/3d3b757b-3460-17ff-3e56-a7e5667e9283/screen768x768.jpeg", 
                                    "width": 576, 
                                    "height": 768
                                }
                            ], 
                            [
                                {
                                    "url": "http://a1.mzstatic.com/us/r30/Purple5/v4/a5/bf/b9/a5bfb952-e0e8-a18c-265d-7ea16f0c0cae/screen261x261-50.jpeg", 
                                    "width": 261, 
                                    "height": 196
                                }, 
                                {
                                    "url": "http://a5.mzstatic.com/us/r30/Purple5/v4/a5/bf/b9/a5bfb952-e0e8-a18c-265d-7ea16f0c0cae/screen460x460.jpeg", 
                                    "width": 460, 
                                    "height": 345
                                }, 
                                {
                                    "url": "http://a4.mzstatic.com/us/r30/Purple5/v4/a5/bf/b9/a5bfb952-e0e8-a18c-265d-7ea16f0c0cae/screen920x920.jpeg", 
                                    "width": 920, 
                                    "height": 690
                                }, 
                                {
                                    "url": "http://a3.mzstatic.com/us/r30/Purple5/v4/a5/bf/b9/a5bfb952-e0e8-a18c-265d-7ea16f0c0cae/screen552x414.jpeg", 
                                    "width": 552, 
                                    "height": 414
                                }, 
                                {
                                    "url": "http://a4.mzstatic.com/us/r30/Purple5/v4/a5/bf/b9/a5bfb952-e0e8-a18c-265d-7ea16f0c0cae/screen420x420.jpeg", 
                                    "width": 420, 
                                    "height": 315
                                }, 
                                {
                                    "url": "http://a2.mzstatic.com/us/r30/Purple5/v4/a5/bf/b9/a5bfb952-e0e8-a18c-265d-7ea16f0c0cae/screen420x316.jpeg", 
                                    "width": 420, 
                                    "height": 315
                                }, 
                                {
                                    "url": "http://a4.mzstatic.com/us/r30/Purple5/v4/a5/bf/b9/a5bfb952-e0e8-a18c-265d-7ea16f0c0cae/screen768x768.jpeg", 
                                    "width": 768, 
                                    "height": 576
                                }
                            ]
                        ], 
                        "iphone5": [
                            [
                                {
                                    "url": "http://a3.mzstatic.com/us/r30/Purple1/v4/44/1a/f9/441af927-df14-5907-38f8-4b2438c37e7c/screen406x722.jpeg", 
                                    "width": 406, 
                                    "height": 721
                                }, 
                                {
                                    "url": "http://a5.mzstatic.com/us/r30/Purple1/v4/44/1a/f9/441af927-df14-5907-38f8-4b2438c37e7c/screen920x920.jpeg", 
                                    "width": 518, 
                                    "height": 920
                                }, 
                                {
                                    "url": "http://a1.mzstatic.com/us/r30/Purple1/v4/44/1a/f9/441af927-df14-5907-38f8-4b2438c37e7c/screen696x696.jpeg", 
                                    "width": 392, 
                                    "height": 696
                                }, 
                                {
                                    "url": "http://a1.mzstatic.com/us/r30/Purple1/v4/44/1a/f9/441af927-df14-5907-38f8-4b2438c37e7c/screen525x296.jpeg", 
                                    "width": 167, 
                                    "height": 296
                                }, 
                                {
                                    "url": "http://a1.mzstatic.com/us/r30/Purple1/v4/44/1a/f9/441af927-df14-5907-38f8-4b2438c37e7c/screen460x460.jpeg", 
                                    "width": 259, 
                                    "height": 460
                                }, 
                                {
                                    "url": "http://a1.mzstatic.com/us/r30/Purple1/v4/44/1a/f9/441af927-df14-5907-38f8-4b2438c37e7c/screen348x348.jpeg", 
                                    "width": 196, 
                                    "height": 348
                                }, 
                                {
                                    "url": "http://a1.mzstatic.com/us/r30/Purple1/v4/44/1a/f9/441af927-df14-5907-38f8-4b2438c37e7c/screen670x377.jpeg", 
                                    "width": 212, 
                                    "height": 377
                                }, 
                                {
                                    "url": "http://a3.mzstatic.com/us/r30/Purple1/v4/44/1a/f9/441af927-df14-5907-38f8-4b2438c37e7c/screen568x568.jpeg", 
                                    "width": 320, 
                                    "height": 568
                                }
                            ], 
                            [
                                {
                                    "url": "http://a4.mzstatic.com/us/r30/Purple1/v4/98/f1/fb/98f1fbf8-f096-2db4-5c46-bb0b9abd62f1/screen406x722.jpeg", 
                                    "width": 406, 
                                    "height": 721
                                }, 
                                {
                                    "url": "http://a4.mzstatic.com/us/r30/Purple1/v4/98/f1/fb/98f1fbf8-f096-2db4-5c46-bb0b9abd62f1/screen920x920.jpeg", 
                                    "width": 518, 
                                    "height": 920
                                }, 
                                {
                                    "url": "http://a5.mzstatic.com/us/r30/Purple1/v4/98/f1/fb/98f1fbf8-f096-2db4-5c46-bb0b9abd62f1/screen696x696.jpeg", 
                                    "width": 392, 
                                    "height": 696
                                }, 
                                {
                                    "url": "http://a5.mzstatic.com/us/r30/Purple1/v4/98/f1/fb/98f1fbf8-f096-2db4-5c46-bb0b9abd62f1/screen525x296.jpeg", 
                                    "width": 167, 
                                    "height": 296
                                }, 
                                {
                                    "url": "http://a5.mzstatic.com/us/r30/Purple1/v4/98/f1/fb/98f1fbf8-f096-2db4-5c46-bb0b9abd62f1/screen460x460.jpeg", 
                                    "width": 259, 
                                    "height": 460
                                }, 
                                {
                                    "url": "http://a5.mzstatic.com/us/r30/Purple1/v4/98/f1/fb/98f1fbf8-f096-2db4-5c46-bb0b9abd62f1/screen348x348.jpeg", 
                                    "width": 196, 
                                    "height": 348
                                }, 
                                {
                                    "url": "http://a5.mzstatic.com/us/r30/Purple1/v4/98/f1/fb/98f1fbf8-f096-2db4-5c46-bb0b9abd62f1/screen670x377.jpeg", 
                                    "width": 212, 
                                    "height": 377
                                }, 
                                {
                                    "url": "http://a4.mzstatic.com/us/r30/Purple1/v4/98/f1/fb/98f1fbf8-f096-2db4-5c46-bb0b9abd62f1/screen568x568.jpeg", 
                                    "width": 320, 
                                    "height": 568
                                }
                            ], 
                            [
                                {
                                    "url": "http://a5.mzstatic.com/us/r30/Purple1/v4/73/74/a7/7374a719-cc98-30ec-8bcb-b5449d9d3b17/screen406x722.jpeg", 
                                    "width": 406, 
                                    "height": 721
                                }, 
                                {
                                    "url": "http://a2.mzstatic.com/us/r30/Purple1/v4/73/74/a7/7374a719-cc98-30ec-8bcb-b5449d9d3b17/screen920x920.jpeg", 
                                    "width": 518, 
                                    "height": 920
                                }, 
                                {
                                    "url": "http://a3.mzstatic.com/us/r30/Purple1/v4/73/74/a7/7374a719-cc98-30ec-8bcb-b5449d9d3b17/screen696x696.jpeg", 
                                    "width": 392, 
                                    "height": 696
                                }, 
                                {
                                    "url": "http://a3.mzstatic.com/us/r30/Purple1/v4/73/74/a7/7374a719-cc98-30ec-8bcb-b5449d9d3b17/screen525x296.jpeg", 
                                    "width": 167, 
                                    "height": 296
                                }, 
                                {
                                    "url": "http://a3.mzstatic.com/us/r30/Purple1/v4/73/74/a7/7374a719-cc98-30ec-8bcb-b5449d9d3b17/screen460x460.jpeg", 
                                    "width": 259, 
                                    "height": 460
                                }, 
                                {
                                    "url": "http://a1.mzstatic.com/us/r30/Purple1/v4/73/74/a7/7374a719-cc98-30ec-8bcb-b5449d9d3b17/screen348x348.jpeg", 
                                    "width": 196, 
                                    "height": 348
                                }, 
                                {
                                    "url": "http://a3.mzstatic.com/us/r30/Purple1/v4/73/74/a7/7374a719-cc98-30ec-8bcb-b5449d9d3b17/screen670x377.jpeg", 
                                    "width": 212, 
                                    "height": 377
                                }, 
                                {
                                    "url": "http://a5.mzstatic.com/us/r30/Purple1/v4/73/74/a7/7374a719-cc98-30ec-8bcb-b5449d9d3b17/screen568x568.jpeg", 
                                    "width": 320, 
                                    "height": 568
                                }
                            ], 
                            [
                                {
                                    "url": "http://a2.mzstatic.com/us/r30/Purple5/v4/13/04/d9/1304d9d0-7a40-a64a-40db-7884d3406353/screen406x722.jpeg", 
                                    "width": 406, 
                                    "height": 721
                                }, 
                                {
                                    "url": "http://a2.mzstatic.com/us/r30/Purple5/v4/13/04/d9/1304d9d0-7a40-a64a-40db-7884d3406353/screen920x920.jpeg", 
                                    "width": 518, 
                                    "height": 920
                                }, 
                                {
                                    "url": "http://a3.mzstatic.com/us/r30/Purple5/v4/13/04/d9/1304d9d0-7a40-a64a-40db-7884d3406353/screen696x696.jpeg", 
                                    "width": 392, 
                                    "height": 696
                                }, 
                                {
                                    "url": "http://a3.mzstatic.com/us/r30/Purple5/v4/13/04/d9/1304d9d0-7a40-a64a-40db-7884d3406353/screen525x296.jpeg", 
                                    "width": 167, 
                                    "height": 296
                                }, 
                                {
                                    "url": "http://a3.mzstatic.com/us/r30/Purple5/v4/13/04/d9/1304d9d0-7a40-a64a-40db-7884d3406353/screen460x460.jpeg", 
                                    "width": 259, 
                                    "height": 460
                                }, 
                                {
                                    "url": "http://a3.mzstatic.com/us/r30/Purple5/v4/13/04/d9/1304d9d0-7a40-a64a-40db-7884d3406353/screen348x348.jpeg", 
                                    "width": 196, 
                                    "height": 348
                                }, 
                                {
                                    "url": "http://a3.mzstatic.com/us/r30/Purple5/v4/13/04/d9/1304d9d0-7a40-a64a-40db-7884d3406353/screen670x377.jpeg", 
                                    "width": 212, 
                                    "height": 377
                                }, 
                                {
                                    "url": "http://a5.mzstatic.com/us/r30/Purple5/v4/13/04/d9/1304d9d0-7a40-a64a-40db-7884d3406353/screen568x568.jpeg", 
                                    "width": 320, 
                                    "height": 568
                                }
                            ], 
                            [
                                {
                                    "url": "http://a5.mzstatic.com/us/r30/Purple3/v4/f1/e9/ca/f1e9ca43-f2c6-748a-b458-b5f8709494d9/screen406x722.jpeg", 
                                    "width": 406, 
                                    "height": 721
                                }, 
                                {
                                    "url": "http://a2.mzstatic.com/us/r30/Purple3/v4/f1/e9/ca/f1e9ca43-f2c6-748a-b458-b5f8709494d9/screen920x920.jpeg", 
                                    "width": 518, 
                                    "height": 920
                                }, 
                                {
                                    "url": "http://a3.mzstatic.com/us/r30/Purple3/v4/f1/e9/ca/f1e9ca43-f2c6-748a-b458-b5f8709494d9/screen696x696.jpeg", 
                                    "width": 392, 
                                    "height": 696
                                }, 
                                {
                                    "url": "http://a1.mzstatic.com/us/r30/Purple3/v4/f1/e9/ca/f1e9ca43-f2c6-748a-b458-b5f8709494d9/screen525x296.jpeg", 
                                    "width": 167, 
                                    "height": 296
                                }, 
                                {
                                    "url": "http://a3.mzstatic.com/us/r30/Purple3/v4/f1/e9/ca/f1e9ca43-f2c6-748a-b458-b5f8709494d9/screen460x460.jpeg", 
                                    "width": 259, 
                                    "height": 460
                                }, 
                                {
                                    "url": "http://a1.mzstatic.com/us/r30/Purple3/v4/f1/e9/ca/f1e9ca43-f2c6-748a-b458-b5f8709494d9/screen348x348.jpeg", 
                                    "width": 196, 
                                    "height": 348
                                }, 
                                {
                                    "url": "http://a3.mzstatic.com/us/r30/Purple3/v4/f1/e9/ca/f1e9ca43-f2c6-748a-b458-b5f8709494d9/screen670x377.jpeg", 
                                    "width": 212, 
                                    "height": 377
                                }, 
                                {
                                    "url": "http://a5.mzstatic.com/us/r30/Purple3/v4/f1/e9/ca/f1e9ca43-f2c6-748a-b458-b5f8709494d9/screen568x568.jpeg", 
                                    "width": 320, 
                                    "height": 568
                                }
                            ]
                        ], 
                        "iphone": [
                            [
                                {
                                    "url": "http://a3.mzstatic.com/us/r30/Purple5/v4/ff/98/95/ff989536-229c-eab0-ddf7-2907a77d42bd/screen263x263.jpeg", 
                                    "width": 175, 
                                    "height": 263
                                }, 
                                {
                                    "url": "http://a1.mzstatic.com/us/r30/Purple5/v4/ff/98/95/ff989536-229c-eab0-ddf7-2907a77d42bd/screen466x466.jpeg", 
                                    "width": 311, 
                                    "height": 466
                                }, 
                                {
                                    "url": "http://a4.mzstatic.com/us/r30/Purple5/v4/ff/98/95/ff989536-229c-eab0-ddf7-2907a77d42bd/screen400x400.jpeg", 
                                    "width": 267, 
                                    "height": 400
                                }, 
                                {
                                    "url": "http://a3.mzstatic.com/us/r30/Purple5/v4/ff/98/95/ff989536-229c-eab0-ddf7-2907a77d42bd/screen526x526.jpeg", 
                                    "width": 351, 
                                    "height": 526
                                }, 
                                {
                                    "url": "http://a3.mzstatic.com/us/r30/Purple5/v4/ff/98/95/ff989536-229c-eab0-ddf7-2907a77d42bd/screen932x932.jpeg", 
                                    "width": 621, 
                                    "height": 932
                                }, 
                                {
                                    "url": "http://a3.mzstatic.com/us/r30/Purple5/v4/ff/98/95/ff989536-229c-eab0-ddf7-2907a77d42bd/screen800x800.jpeg", 
                                    "width": 533, 
                                    "height": 800
                                }
                            ], 
                            [
                                {
                                    "url": "http://a1.mzstatic.com/us/r30/Purple3/v4/cc/22/4a/cc224a68-8753-65da-f47c-824fe61a2d57/screen263x263.jpeg", 
                                    "width": 175, 
                                    "height": 263
                                }, 
                                {
                                    "url": "http://a4.mzstatic.com/us/r30/Purple3/v4/cc/22/4a/cc224a68-8753-65da-f47c-824fe61a2d57/screen466x466.jpeg", 
                                    "width": 311, 
                                    "height": 466
                                }, 
                                {
                                    "url": "http://a2.mzstatic.com/us/r30/Purple3/v4/cc/22/4a/cc224a68-8753-65da-f47c-824fe61a2d57/screen400x400.jpeg", 
                                    "width": 267, 
                                    "height": 400
                                }, 
                                {
                                    "url": "http://a1.mzstatic.com/us/r30/Purple3/v4/cc/22/4a/cc224a68-8753-65da-f47c-824fe61a2d57/screen526x526.jpeg", 
                                    "width": 351, 
                                    "height": 526
                                }, 
                                {
                                    "url": "http://a1.mzstatic.com/us/r30/Purple3/v4/cc/22/4a/cc224a68-8753-65da-f47c-824fe61a2d57/screen932x932.jpeg", 
                                    "width": 621, 
                                    "height": 932
                                }, 
                                {
                                    "url": "http://a1.mzstatic.com/us/r30/Purple3/v4/cc/22/4a/cc224a68-8753-65da-f47c-824fe61a2d57/screen800x800.jpeg", 
                                    "width": 533, 
                                    "height": 800
                                }
                            ], 
                            [
                                {
                                    "url": "http://a1.mzstatic.com/us/r30/Purple3/v4/ff/52/12/ff5212f1-f949-ecec-5833-3b218b73c39e/screen263x263.jpeg", 
                                    "width": 175, 
                                    "height": 263
                                }, 
                                {
                                    "url": "http://a4.mzstatic.com/us/r30/Purple3/v4/ff/52/12/ff5212f1-f949-ecec-5833-3b218b73c39e/screen466x466.jpeg", 
                                    "width": 311, 
                                    "height": 466
                                }, 
                                {
                                    "url": "http://a2.mzstatic.com/us/r30/Purple3/v4/ff/52/12/ff5212f1-f949-ecec-5833-3b218b73c39e/screen400x400.jpeg", 
                                    "width": 267, 
                                    "height": 400
                                }, 
                                {
                                    "url": "http://a1.mzstatic.com/us/r30/Purple3/v4/ff/52/12/ff5212f1-f949-ecec-5833-3b218b73c39e/screen526x526.jpeg", 
                                    "width": 351, 
                                    "height": 526
                                }, 
                                {
                                    "url": "http://a1.mzstatic.com/us/r30/Purple3/v4/ff/52/12/ff5212f1-f949-ecec-5833-3b218b73c39e/screen932x932.jpeg", 
                                    "width": 621, 
                                    "height": 932
                                }, 
                                {
                                    "url": "http://a1.mzstatic.com/us/r30/Purple3/v4/ff/52/12/ff5212f1-f949-ecec-5833-3b218b73c39e/screen800x800.jpeg", 
                                    "width": 533, 
                                    "height": 800
                                }
                            ], 
                            [
                                {
                                    "url": "http://a3.mzstatic.com/us/r30/Purple3/v4/39/5c/fd/395cfdba-d35a-fb9c-b8db-5e641df62c1e/screen263x263.jpeg", 
                                    "width": 175, 
                                    "height": 263
                                }, 
                                {
                                    "url": "http://a1.mzstatic.com/us/r30/Purple3/v4/39/5c/fd/395cfdba-d35a-fb9c-b8db-5e641df62c1e/screen466x466.jpeg", 
                                    "width": 311, 
                                    "height": 466
                                }, 
                                {
                                    "url": "http://a4.mzstatic.com/us/r30/Purple3/v4/39/5c/fd/395cfdba-d35a-fb9c-b8db-5e641df62c1e/screen400x400.jpeg", 
                                    "width": 267, 
                                    "height": 400
                                }, 
                                {
                                    "url": "http://a3.mzstatic.com/us/r30/Purple3/v4/39/5c/fd/395cfdba-d35a-fb9c-b8db-5e641df62c1e/screen526x526.jpeg", 
                                    "width": 351, 
                                    "height": 526
                                }, 
                                {
                                    "url": "http://a3.mzstatic.com/us/r30/Purple3/v4/39/5c/fd/395cfdba-d35a-fb9c-b8db-5e641df62c1e/screen932x932.jpeg", 
                                    "width": 621, 
                                    "height": 932
                                }, 
                                {
                                    "url": "http://a3.mzstatic.com/us/r30/Purple3/v4/39/5c/fd/395cfdba-d35a-fb9c-b8db-5e641df62c1e/screen800x800.jpeg", 
                                    "width": 533, 
                                    "height": 800
                                }
                            ], 
                            [
                                {
                                    "url": "http://a3.mzstatic.com/us/r30/Purple3/v4/78/a4/03/78a4039c-d20b-f5be-4786-95a8fc74b35a/screen263x263.jpeg", 
                                    "width": 175, 
                                    "height": 263
                                }, 
                                {
                                    "url": "http://a3.mzstatic.com/us/r30/Purple3/v4/78/a4/03/78a4039c-d20b-f5be-4786-95a8fc74b35a/screen466x466.jpeg", 
                                    "width": 311, 
                                    "height": 466
                                }, 
                                {
                                    "url": "http://a1.mzstatic.com/us/r30/Purple3/v4/78/a4/03/78a4039c-d20b-f5be-4786-95a8fc74b35a/screen400x400.jpeg", 
                                    "width": 267, 
                                    "height": 400
                                }, 
                                {
                                    "url": "http://a5.mzstatic.com/us/r30/Purple3/v4/78/a4/03/78a4039c-d20b-f5be-4786-95a8fc74b35a/screen526x526.jpeg", 
                                    "width": 351, 
                                    "height": 526
                                }, 
                                {
                                    "url": "http://a5.mzstatic.com/us/r30/Purple3/v4/78/a4/03/78a4039c-d20b-f5be-4786-95a8fc74b35a/screen932x932.jpeg", 
                                    "width": 621, 
                                    "height": 932
                                }, 
                                {
                                    "url": "http://a3.mzstatic.com/us/r30/Purple3/v4/78/a4/03/78a4039c-d20b-f5be-4786-95a8fc74b35a/screen800x800.jpeg", 
                                    "width": 533, 
                                    "height": 800
                                }
                            ]
                        ]
                    }, 
                    "videoPreviewByType": {}, 
                    "newsstandArtwork": null, 
                    "isFirstParty": false
                }
            }, 
            "isAuthenticated": false
        }
    }, 
    "properties": {
        "ITSResourceRevNum": "9548", 
        "isCobaltJavascriptRedirectEnabled": true, 
        "isModern": false, 
        "ITSLogger.ServerReportingApp": "MZUserXP", 
        "MZFeatureEnabler.isSoftwareGiftingEnabledForStoreFront": true, 
        "ITSServerEnvironment": "prod", 
        "SF6.Personalization.isCMAEnabled": true, 
        "SF6.Personalization.isCMSEnabled": true, 
        "cobaltBundleId": "com.apple.itunesu", 
        "ITSLogger.SenderName": "ITSClient", 
        "ITSServerInstance": "2125797", 
        "iTunesUEnrollLink": "https://itunes.apple.com/WebObjects/DZR.woa/wa/iTunesEnrollPopover?cc=us", 
        "isDesktopBuyingGiftCertificateEnabled": true, 
        "getCobaltAppLink": "https://itunes.apple.com/us/app/id490217893", 
        "isCobaltEnabled": true, 
        "resourceUrlPrefix": "https://s.mzstatic.com", 
        "SF6.Metrics.ReportingSuite": "appleitmswww,appleitmsus", 
        "SF.StorePlatform.PersonalizationEnabledViaStorePlatform": false, 
        "clientStatsLoadTimeGroup": "4006", 
        "DI6.isTypEnabled": true, 
        "MetricsEventPage.extRefUrlTTL": 30, 
        "DynaLoader.allowDynaLoading": true, 
        "MZFeatureEnabler.isEcommerceInfoEnabled": false, 
        "ITSLogger.RecordStatsAction": "recordStats", 
        "itsLoggerQueueProcessingInterval": 10000, 
        "MZFeatureEnabler.isHDMovieGiftingEnabledForStoreFront": true, 
        "MZStore.shouldAttemptToEvaluateXpathSecondTime": true, 
        "ITSLogger.ServerReportingDomain": "metrics.mzstatic.com", 
        "isDesktopAllowanceCreationEnabled": true, 
        "personalizedButtonsEnabled": true, 
        "vendLastSupportedVersionMacOs": true, 
        "vendLastSupportedVersionIfAvailable": true, 
        "SF.StorePlatform.PersonalizationEnabledViaStorePlatformForVips": [], 
        "metrics": {
            "metricsUrl": "https://xp.apple.com/report", 
            "metricsBase": {
                "language": "1", 
                "platformId": "28", 
                "storeFront": "143441", 
                "storeFrontHeader": "143441-1,28", 
                "environmentDataCenter": "ST11", 
                "platformName": "iTunes12"
            }, 
            "postFrequency": 60000, 
            "blacklistedFields": [
                "capacitySystem", 
                "capacitySystemAvailable", 
                "capacityDisk", 
                "capacityData", 
                "capacityDataAvailable"
            ], 
            "compoundSeparator": "_", 
            "tokenSeparator": "|", 
            "fieldsMap": {
                "single": {
                    "targetId": [
                        "id", 
                        "adamId", 
                        "contentId", 
                        "type", 
                        "fcId", 
                        "station-hash"
                    ]
                }, 
                "multi": {}, 
                "cookies": [
                    "itcCt"
                ], 
                "custom": {
                    "impressions": [
                        "id", 
                        "adamId", 
                        "station-hash"
                    ], 
                    "location": [
                        "id", 
                        "adamId", 
                        "dataSetId", 
                        "name", 
                        "fcKind", 
                        "kindIds", 
                        "type", 
                        "station-hash", 
                        "core-seed-name"
                    ]
                }
            }
        }, 
        "MZHtmlResourcesUtil.allowDeferJsLoad": true, 
        "isCobaltUpsellPageEnabled": true, 
        "cobaltLearnMore": "https://itunes.apple.com/us/learn-more?about=iTunesUUpgradePage&type=2", 
        "isDesktopGiftingEnabled": true, 
        "isRadioHistoryEnabled": true, 
        "ITSLogger.ServerReportingProtocol": "https", 
        "SF.StorePlatform.PersonalizationEnabled": true, 
        "SF6.StorePlatform.whitelistParams": [
            "caller", 
            "dsid", 
            "id", 
            "p"
        ], 
        "SFJ.isNFAEnabledInStorefront": true, 
        "MZFeatureEnabler.isMovieGiftingEnabledForStoreFront": true, 
        "resourcesPreloaded": "true", 
        "MZStore.shouldCacheElementTypeProtoObjects": true, 
        "ITSLogger.mirrorToServerByDefaultOnErrors": true, 
        "isSiriTagHistoryEnabled": true, 
        "isBookGiftingEnabled": true
    }, 
    "constants": {
        "languageCode": "en", 
        "DZC": {
            "url": "https://dzc-metrics.mzstatic.com/WebObjects/DZC.woa/wa/report"
        }, 
        "addToWishListBaseUrl": "https://se.itunes.apple.com/WebObjects/MZStoreElements.woa/wa/addToWishlist", 
        "sortBaseUrl": "https://itunes.apple.com/WebObjects/MZStore.woa/wa/sort", 
        "linkAccountSrvUrl": "https://buy.itunes.apple.com/WebObjects/MZFinance.woa/wa/linkAccountSrv", 
        "iTunesLPLearnMoreUrl": "https://itunes.apple.com/WebObjects/MZStore.woa/wa/viewStaticPage?name=LearnMore_iTunesLP", 
        "AddToWishlistResult": {
            "Success": {
                "id": 0
            }, 
            "ListFull": {
                "id": 3
            }, 
            "ItemIsFree": {
                "id": 6
            }, 
            "SomeContentAlreadyOwnedButUnfulfilled": {
                "id": 5
            }, 
            "SomeContentAlreadyOwned": {
                "id": 4
            }, 
            "Failure": {
                "id": 2
            }, 
            "SomeContentAlreadyInWishlist": {
                "id": 1
            }
        }, 
        "appRatingsLearnMoreUrl": "https://itunes.apple.com/WebObjects/MZStore.woa/wa/appRatings?cc=us", 
        "getEmailUrl": "https://itunes.apple.com/WebObjects/MZStore.woa/wa/generateEmail?cc=us", 
        "DT6.GetUserFullNameUrl": "https://se.itunes.apple.com/WebObjects/MZStoreElements.woa/wa/getUserFullName", 
        "tellAFriendBaseUrl": "https://userpub.itunes.apple.com/WebObjects/MZUserPublishing.woa/wa/tellAFriendSubmit", 
        "giftPageData": "https://itunes.apple.com/WebObjects/MZStore.woa/wa/giftPageData", 
        "countryCode": "usa", 
        "GlobalLists": {
            "removeFromWishlistUrl": "https://se.itunes.apple.com/WebObjects/MZStoreElements.woa/wa/removeFromWishlist", 
            "viewUrl": "https://itunes.apple.com/WebObjects/MZStore.woa/wa/viewGlobalLists?revNum=9548", 
            "updateRadioHistoryUrl": "https://se.itunes.apple.com/WebObjects/MZStoreElements.woa/wa/updateRadioHistory", 
            "popover": {
                "width": "350", 
                "maxWishlistItemCount": 20, 
                "height": "70%"
            }, 
            "viewWishlistUrl": "https://se.itunes.apple.com/WebObjects/MZStoreElements.woa/wa/viewWishlist?cc=us", 
            "updateSiriTagHistoryUrl": "https://se.itunes.apple.com/WebObjects/MZStoreElements.woa/wa/updateSiriTagHistory", 
            "updatePreviewHistoryUrl": "https://se.itunes.apple.com/WebObjects/MZStoreElements.woa/wa/updatePreviewHistory"
        }, 
        "buyButtonMetaDataBaseUrl": "https://se.itunes.apple.com/WebObjects/MZStoreElements.woa/wa/buyButtonMetaData", 
        "MZMediaType": {
            "Audiobooks": {
                "id": 3, 
                "name": "Audiobooks"
            }, 
            "MacSoftware": {
                "id": 12, 
                "name": "DesktopApps"
            }, 
            "TVShows": {
                "id": 4, 
                "name": "TVShows"
            }, 
            "Ringtones": {
                "id": 9, 
                "name": "Ringtones"
            }, 
            "Podcasts": {
                "id": 2, 
                "name": "Podcasts"
            }, 
            "iTunesU": {
                "id": 10, 
                "name": "iTunesU"
            }, 
            "Movies": {
                "id": 6, 
                "name": "Movies"
            }, 
            "Music": {
                "id": 1, 
                "name": "Music"
            }, 
            "MusicVideos": {
                "id": 5, 
                "name": "MusicVideos"
            }, 
            "ClassicSoftware": {
                "id": 7, 
                "name": "iPodGames"
            }, 
            "EBooks": {
                "id": 11, 
                "name": "EBooks"
            }, 
            "MobileSoftware": {
                "id": 8, 
                "name": "MobileSoftwareApplications"
            }
        }, 
        "getScheduledGifts": "https://buy.itunes.apple.com/WebObjects/MZFinance.woa/wa/getScheduledGiftsSrv", 
        "IXDisplayableKind": {
            "Album": {
                "mtId": "1", 
                "id": 2, 
                "name": "album", 
                "cssClasses": [
                    "album", 
                    "music"
                ]
            }, 
            "MacSoftware": {
                "mtId": "12", 
                "id": 30, 
                "name": "desktopApp", 
                "cssClasses": [
                    "application", 
                    "mac-application"
                ]
            }, 
            "RingtoneAlbum": {
                "mtId": "9", 
                "id": 22, 
                "name": "ringtoneAlbum", 
                "cssClasses": []
            }, 
            "SocialArtist": {
                "id": 28, 
                "name": "socialArtist", 
                "cssClasses": []
            }, 
            "Movie": {
                "mtId": "6", 
                "id": 9, 
                "name": "movie", 
                "cssClasses": [
                    "movie", 
                    "video"
                ]
            }, 
            "MovieBundle": {
                "mtId": "6", 
                "id": 24, 
                "name": "movieBundle", 
                "cssClasses": [
                    "bundle", 
                    "movie", 
                    "video"
                ]
            }, 
            "Ringtone": {
                "mtId": "9", 
                "id": 21, 
                "name": "ringtone", 
                "cssClasses": []
            }, 
            "Mix": {
                "mtId": "1", 
                "id": 14, 
                "name": "mix", 
                "cssClasses": [
                    "mix", 
                    "music"
                ]
            }, 
            "Book": {
                "mtId": "3", 
                "id": 3, 
                "name": "book", 
                "cssClasses": [
                    "audiobook"
                ]
            }, 
            "SocialPerson": {
                "id": 27, 
                "name": "socialPerson", 
                "cssClasses": []
            }, 
            "ApplePubTextbook": {
                "mtId": "13", 
                "id": 37, 
                "name": "ibookTextbook", 
                "cssClasses": [
                    "ebook"
                ]
            }, 
            "TVEpisode": {
                "mtId": "4", 
                "id": 6, 
                "name": "tvEpisode", 
                "cssClasses": [
                    "tv-episode", 
                    "tv", 
                    "video"
                ]
            }, 
            "MobileSoftware": {
                "mtId": "8", 
                "id": 11, 
                "name": "iosSoftware", 
                "cssClasses": [
                    "application"
                ]
            }, 
            "TVSeason": {
                "mtId": "4", 
                "id": 7, 
                "name": "tvSeason", 
                "cssClasses": [
                    "tv-season", 
                    "tv", 
                    "video"
                ]
            }, 
            "Song": {
                "mtId": "1", 
                "id": 1, 
                "name": "song", 
                "cssClasses": [
                    "song", 
                    "music"
                ]
            }, 
            "Booklet": {
                "mtId": "1", 
                "id": 13, 
                "name": "booklet", 
                "cssClasses": [
                    "booklet", 
                    "music"
                ]
            }, 
            "ToneAlbum": {
                "mtId": "9", 
                "id": 32, 
                "name": "toneAlbum", 
                "cssClasses": []
            }, 
            "SoftwareAddOn": {
                "mtId": "8", 
                "id": 16, 
                "name": "softwareAddOn", 
                "cssClasses": [
                    "software-add-on", 
                    "application"
                ]
            }, 
            "Podcast": {
                "mtId": "2", 
                "id": 4, 
                "name": "podcast", 
                "cssClasses": [
                    "podcast"
                ]
            }, 
            "MetaEBook": {
                "mtId": "13", 
                "id": 35, 
                "name": "metaEbook", 
                "cssClasses": [
                    "ebook"
                ]
            }, 
            "EBook": {
                "mtId": "11", 
                "id": 25, 
                "name": "epubBook", 
                "cssClasses": [
                    "ebook"
                ]
            }, 
            "Artist": {
                "id": 20, 
                "name": "artist", 
                "cssClasses": []
            }, 
            "ApplePubEBook": {
                "mtId": "11", 
                "id": 36, 
                "name": "ibook", 
                "cssClasses": [
                    "ebook"
                ]
            }, 
            "TheyMix": {
                "id": 33, 
                "name": "thirdPartyMix", 
                "cssClasses": []
            }, 
            "iTunesPass": {
                "mtId": "1", 
                "id": 12, 
                "name": "itunesPass", 
                "cssClasses": [
                    "itunes-pass", 
                    "album", 
                    "music"
                ]
            }, 
            "ShortFilm": {
                "mtId": "6", 
                "id": 8, 
                "name": "shortFilm", 
                "cssClasses": [
                    "short-film", 
                    "movie", 
                    "video"
                ]
            }, 
            "ClassicSoftwarePackage": {
                "mtId": "7", 
                "id": 18, 
                "name": "gamePackage", 
                "cssClasses": [
                    "ipod-game"
                ]
            }, 
            "Tone": {
                "mtId": "9", 
                "id": 31, 
                "name": "tone", 
                "cssClasses": []
            }, 
            "Concert": {
                "mtId": "1", 
                "id": 26, 
                "name": "concert", 
                "cssClasses": []
            }, 
            "MusicVideo": {
                "mtId": "5", 
                "id": 5, 
                "name": "musicVideo", 
                "cssClasses": [
                    "music-video", 
                    "music", 
                    "video"
                ]
            }, 
            "Course": {
                "mtId": "10", 
                "id": 34, 
                "name": "course", 
                "cssClasses": [
                    "course", 
                    "itunes-u"
                ]
            }, 
            "WeMix": {
                "mtId": "1", 
                "id": 19, 
                "name": "itunesMix", 
                "cssClasses": [
                    "wemix", 
                    "music"
                ]
            }, 
            "ClassicSoftware": {
                "mtId": "7", 
                "id": 10, 
                "name": "ipodGame", 
                "cssClasses": [
                    "ipod-game"
                ]
            }, 
            "PodcastEpisode": {
                "mtId": "2", 
                "id": 15, 
                "name": "podcastEpisode", 
                "cssClasses": [
                    "podcast-episode"
                ]
            }
        }, 
        "twitterShareUrl": "https://itunes.apple.com/WebObjects/MZStore.woa/wa/twitterShare?cc=us", 
        "giftBaseUrl": "https://buy.itunes.apple.com/WebObjects/MZFinance.woa/wa/giftItem", 
        "SFCustomComponentCountryCode": "usa", 
        "removeFromWishlistUrl": "https://se.itunes.apple.com/WebObjects/MZStoreElements.woa/wa/removeFromWishlist", 
        "its.sf.StorePlatform.personalizationQueueTime": null, 
        "SFSortOrder": {
            "CmcRecommended": {
                "id": 10
            }, 
            "DateAdded": {
                "id": 15
            }, 
            "Name": {
                "id": 0
            }, 
            "PurchaseDate": {
                "id": 4
            }, 
            "Price": {
                "id": 7
            }, 
            "Popularity": {
                "id": 3
            }, 
            "RecentBestSellers": {
                "id": 18
            }, 
            "TopRated": {
                "id": 5
            }, 
            "MostRecent": {
                "id": 16
            }, 
            "ReleaseDate": {
                "id": 2
            }, 
            "AllTimeBestSellers": {
                "id": 14
            }, 
            "PlaylistName": {
                "id": 9
            }, 
            "ExpirationDate": {
                "id": 6
            }, 
            "ArtistName": {
                "id": 8
            }, 
            "Duration": {
                "id": 11
            }, 
            "TrackNumber": {
                "id": 13
            }, 
            "DiscNumber": {
                "id": 12
            }, 
            "Featured": {
                "id": 1
            }, 
            "SeriesOrder": {
                "id": 17
            }
        }, 
        "parentalAdvisoryUrl": "https://itunes.apple.com/WebObjects/MZStore.woa/wa/parentalAdvisory?cc=us", 
        "its.sf.StorePlatform.disablePersonalizationQueue": false, 
        "iTunesExtrasLearnMoreUrl": "https://itunes.apple.com/WebObjects/MZStore.woa/wa/viewStaticPage?name=LearnMore_iTunesExtras", 
        "SFEntityType": {
            "Search": {
                "id": 6
            }, 
            "Work": {
                "id": 10
            }, 
            "Room": {
                "id": 5
            }, 
            "Playlist": {
                "id": 4
            }, 
            "Artist": {
                "id": 1
            }, 
            "TheyMix": {
                "id": 11
            }, 
            "Cmc": {
                "id": 2
            }, 
            "TopAuthors": {
                "id": 12
            }, 
            "TopContents": {
                "id": 7
            }, 
            "MultiRoom": {
                "id": 3
            }, 
            "WeMix": {
                "id": 8
            }, 
            "Wishlist": {
                "id": 9
            }
        }, 
        "sortPersonalizedBaseUrl": "https://se.itunes.apple.com/WebObjects/MZStoreElements.woa/wa/sort", 
        "videoAdvisoryUrl": "https://itunes.apple.com/WebObjects/MZStore.woa/wa/movieTvRatingsAdvisory?cc=us", 
        "redirectToSignupWizard": "https://buy.itunes.apple.com/WebObjects/MZFinance.woa/wa/redirectToSignupWizard", 
        "hdTvLearnMoreUrl": "https://itunes.apple.com/WebObjects/MZStore.woa/wa/HDTVLearnMorePage", 
        "storePlatformLookupUrl": "https://client-api.itunes.apple.com/WebObjects/MZStorePlatform.woa/wa/lookup?version=1", 
        "checkForPreorders": "https://buy.itunes.apple.com/WebObjects/MZFinance.woa/wa/checkForPreorders"
    }
}